<?xml version="1.0"?>
<?xml-stylesheet type="text/xsl" href="billres.xsl"?>
<!DOCTYPE bill PUBLIC "-//US Congress//DTDs/bill.dtd//EN" "bill.dtd">
<bill bill-stage="Introduced-in-Senate" dms-id="A1" public-private="public" slc-id="S1-OTT26034-VPX-L9-0D4"><metadata xmlns:dc="http://purl.org/dc/elements/1.1/">
<dublinCore>
<dc:title>119 S4292 IS: Improving Retirement Security for Family Caregivers Act of 2026</dc:title>
<dc:publisher>U.S. Senate</dc:publisher>
<dc:date>2026-04-14</dc:date>
<dc:format>text/xml</dc:format>
<dc:language>EN</dc:language>
<dc:rights>Pursuant to Title 17 Section 105 of the United States Code, this file is not subject to copyright protection and is in the public domain.</dc:rights>
</dublinCore>
</metadata>
<form>
<distribution-code display="yes">II</distribution-code><congress>119th CONGRESS</congress><session>2d Session</session><legis-num>S. 4292</legis-num><current-chamber>IN THE SENATE OF THE UNITED STATES</current-chamber><action><action-date date="20260414">April 14, 2026</action-date><action-desc><sponsor name-id="S252">Ms. Collins</sponsor> (for herself and <cosponsor name-id="S327">Mr. Warner</cosponsor>) introduced the following bill; which was read twice and referred to the <committee-name committee-id="SSFI00">Committee on Finance</committee-name></action-desc></action><legis-type>A BILL</legis-type><official-title>To amend the Internal Revenue Code of 1986 to allow certain family caregivers to contribute to a Roth IRA.</official-title></form><legis-body display-enacting-clause="yes-display-enacting-clause"><section section-type="section-one" id="S1"><enum>1.</enum><header>Short title</header><text display-inline="no-display-inline">This Act may be cited as the <quote><short-title>Improving Retirement Security for Family Caregivers Act of 2026</short-title></quote>.</text></section><section commented="no" display-inline="no-display-inline" id="id4b511d475d82498aa93b67d0bfd4f997"><enum>2.</enum><header>Roth IRA contributions for certain family caregivers</header><subsection commented="no" display-inline="no-display-inline" id="id896fb0c4e5d14ebba3750615cb8aa0ac"><enum>(a)</enum><header>In general</header><text>Subsection (c) of <external-xref legal-doc="usc" parsable-cite="usc/26/408A">section 408A</external-xref> of the Internal Revenue Code of 1986 is amended by adding at the end the following new paragraph:</text><quoted-block style="OLC" display-inline="no-display-inline" id="idAAA9FB1289A041238D78B1C04EBDA668"><paragraph commented="no" display-inline="no-display-inline" id="id58ad18015af444a6850215b758a5156d"><enum>(7)</enum><header>Special rule for Roth IRA contributions of qualified family caregivers</header><subparagraph commented="no" display-inline="no-display-inline" id="id95ae1feb0ec1473bb4ebf4cfb883c720"><enum>(A)</enum><header display-inline="yes-display-inline">In general</header><text>In the case of an individual who is a qualified family caregiver as of the close of the taxable year, in applying section 219 for purposes of paragraph (2), the limitation of paragraph (1) of section 219(b) shall be equal to the dollar amount in effect under section 219(b)(1)(A) for the taxable year.</text></subparagraph><subparagraph id="id690d4f96cbcc4e348c3d73240a7c3271"><enum>(B)</enum><header>Qualified family caregiver</header><text>For purposes of this paragraph—</text><clause commented="no" display-inline="no-display-inline" id="id05e236a2e1c34a5ba9fb3ec1e73a157d"><enum>(i)</enum><header>In general</header><text>The term <term>qualified family caregiver</term> means an individual who, during the taxable year—</text><subclause commented="no" display-inline="no-display-inline" id="id24C61412D6D248DAB62774BA3D5D6EF9"><enum>(I)</enum><text>has completed 500 or more hours as a family caregiver, and</text></subclause><subclause commented="no" display-inline="no-display-inline" id="idDF8209FC54B74F13BC4DCFE2A832937F"><enum>(II)</enum><text>has completed fewer than 500 hours of paid employment (including self-employment).</text></subclause></clause><clause id="id70e19cfe41ef477a8f7b7e1089621542"><enum>(ii)</enum><header>Family caregiver</header><text>The term <term>family caregiver</term> means an unpaid family member, a foster parent, or another unpaid adult, who is unemployed or severely underemployed (as determined by the Secretary) and who provides in-home care, monitoring, management, supervision, or treatment of—</text><subclause commented="no" display-inline="no-display-inline" id="idbe4afccfea7a482c988117b149c1e317"><enum>(I)</enum><text display-inline="yes-display-inline">a child, or </text></subclause><subclause commented="no" display-inline="no-display-inline" id="id7cf7ba8ea67d41789c99d63ac0f62913"><enum>(II)</enum><text display-inline="yes-display-inline">an adult with a special need (as defined in section 2901 of the Public Health Service Act), including an elderly adult who requires care or supervision due to an age-related condition.</text></subclause></clause><clause id="id2671f505101a45838a625098af0d1c4e"><enum>(iii)</enum><header>Hours</header><text>An individual shall be treated as serving as a family caregiver during the hours in which the individual is engaged in caregiving tasks including assistance with bathing or grooming, dressing, laundry, food shopping or preparation, housekeeping, managing medications, transportation, and mobility assistance.</text></clause></subparagraph><subparagraph commented="no" display-inline="no-display-inline" id="id0A75821D89A748B78A685CFA45B97E2E"><enum>(C)</enum><header>Coordination with spousal IRA</header><text display-inline="yes-display-inline">In the case of an individual to whom section 219(c)(1) applies for the taxable year, subparagraph (A) shall be applied notwithstanding such section.</text></subparagraph></paragraph><after-quoted-block>.</after-quoted-block></quoted-block></subsection><subsection id="id66f5aaea41d44db38d48df58791a7145"><enum>(b)</enum><header>Effective date</header><text>The amendment made by this section shall apply to taxable years beginning after December 31, 2025.</text></subsection></section></legis-body></bill> 

