{
  "action": {
    "description": "The resolution provides for consideration of H.R. 2988 under a structured rule, and H.R. 2262, H.R. 2270, H.R. 2312, and H.R. 4366 under a closed rule. The rule provides for one hour of general debate and one motion to recommit on each bill.",
    "occurred_at": "2026-01-12T23:48:32+00:00",
    "jurisdiction_id": "~{\"classification\": \"lower\"}",
    "session_id": "119",
    "entity_type": "bill",
    "classifications": [],
    "related_entities": [],
    "sources": [
      {
        "url": "https://www.govinfo.gov/bulkdata/BILLSTATUS/119/hres/BILLSTATUS-119hres988.xml",
        "note": ""
      },
      {
        "url": "https://congress.gov/bill/119th-congress/house-resolution/988",
        "note": ""
      }
    ]
  },
  "bill_id": "HRES 988"
}