{
  "action": {
    "description": "Considered as unfinished business. (consideration: CR H4393)",
    "occurred_at": "2025-09-17T21:30:34+00:00",
    "jurisdiction_id": "~{\"classification\": \"lower\"}",
    "session_id": "119",
    "entity_type": "bill",
    "classifications": [],
    "related_entities": [],
    "sources": [
      {
        "url": "https://www.govinfo.gov/bulkdata/BILLSTATUS/119/hres/BILLSTATUS-119hres722.xml",
        "note": ""
      },
      {
        "url": "https://congress.gov/bill/119th-congress/house-resolution/722",
        "note": ""
      }
    ]
  },
  "bill_id": "HRES 722"
}