{
  "action": {
    "description": "Introduced in Senate",
    "occurred_at": "2026-03-18T04:00:00+00:00",
    "jurisdiction_id": "~{\"classification\": \"upper\"}",
    "session_id": "119",
    "entity_type": "bill",
    "classifications": [
      "introduction"
    ],
    "related_entities": [],
    "sources": [
      {
        "url": "https://www.govinfo.gov/bulkdata/BILLSTATUS/119/s/BILLSTATUS-119s4128.xml",
        "note": ""
      },
      {
        "url": "https://congress.gov/bill/119th-congress/senate-bill/4128",
        "note": ""
      }
    ]
  },
  "bill_id": "S 4128"
}