{
  "action": {
    "description": "On passage Passed by the Yeas and Nays: 220 - 206, 1 Present (Roll no. 52). (text: CR H846)",
    "occurred_at": "2025-02-26T21:45:30+00:00",
    "jurisdiction_id": "~{\"classification\": \"lower\"}",
    "session_id": "119",
    "entity_type": "bill",
    "classifications": [],
    "related_entities": [],
    "sources": [
      {
        "url": "https://www.govinfo.gov/bulkdata/BILLSTATUS/119/hjres/BILLSTATUS-119hjres35.xml",
        "note": ""
      },
      {
        "url": "https://congress.gov/bill/119th-congress/house-joint-resolution/35",
        "note": ""
      }
    ]
  },
  "bill_id": "HJRES 35"
}