<?xml version="1.0"?>
<?xml-stylesheet type="text/xsl" href="billres.xsl"?>
<!DOCTYPE bill PUBLIC "-//US Congress//DTDs/bill.dtd//EN" "bill.dtd">
<bill bill-stage="Introduced-in-House" dms-id="H9FB78050E30C48A4BC605837EF28A0B8" public-private="public" key="H" bill-type="olc"><metadata xmlns:dc="http://purl.org/dc/elements/1.1/">
<dublinCore>
<dc:title>119 HR 8959 IH: Semiconductor Superiority Act</dc:title>
<dc:publisher>U.S. House of Representatives</dc:publisher>
<dc:date>2026-05-21</dc:date>
<dc:format>text/xml</dc:format>
<dc:language>EN</dc:language>
<dc:rights>Pursuant to Title 17 Section 105 of the United States Code, this file is not subject to copyright protection and is in the public domain.</dc:rights>
</dublinCore>
</metadata>
<form>
<distribution-code display="yes">I</distribution-code><congress display="yes">119th CONGRESS</congress><session display="yes">2d Session</session><legis-num display="yes">H. R. 8959</legis-num><current-chamber>IN THE HOUSE OF REPRESENTATIVES</current-chamber><action display="yes"><action-date date="20260521">May 21, 2026</action-date><action-desc><sponsor name-id="B001260">Mr. Buchanan</sponsor> (for himself, <cosponsor name-id="S001185">Ms. Sewell</cosponsor>, and <cosponsor name-id="D000617">Ms. DelBene</cosponsor>) introduced the following bill; which was referred to the <committee-name committee-id="HWM00">Committee on Ways and Means</committee-name></action-desc></action><legis-type>A BILL</legis-type><official-title display="yes">To amend the Internal Revenue Code of 1986 to clarify the application of the advanced manufacturing investment credit with respect to semiconductor manufacturing facilities located in outer space.</official-title></form><legis-body id="H38F8F0BA4BC44B66BEA569502ABF5DAB" style="OLC"> 
<section id="HFD03ECB1624C4F9BA8D4DABF6E3CD968" section-type="section-one"><enum>1.</enum><header>Short title</header><text display-inline="no-display-inline">This Act may be cited as the <quote><short-title>Semiconductor Superiority Act</short-title></quote>.</text></section> <section commented="no" display-inline="no-display-inline" id="HF4181FC5B84549A7BB6ACF8184886E08"><enum>2.</enum><header>Clarifying application of advanced manufacturing investment credit for semiconductor manufacturing facilities located in outer space</header> <subsection commented="no" display-inline="no-display-inline" id="H5BE138B715E54CCCB59150E1B2C6C600"><enum>(a)</enum><header>In general</header><text><external-xref legal-doc="usc" parsable-cite="usc/26/48D">Section 48D(b)</external-xref> of the Internal Revenue Code of 1986 is amended by adding at the end the following new paragraph:</text> 
<quoted-block style="OLC" display-inline="no-display-inline" id="H85590E45066042B4B1F133DAED86CCEA"> 
<paragraph id="H0AAD75927C034AACB5B4A4ABCF28E3EC"><enum>(6)</enum><header>Application to facilities located in outer space</header> 
<subparagraph commented="no" display-inline="no-display-inline" id="HD0055332EA17446F9E6807E6531E74A4"><enum>(A)</enum><header display-inline="yes-display-inline">In general</header><text>In the case of an advanced manufacturing facility which is located in outer space—</text> <clause commented="no" display-inline="no-display-inline" id="HA47894833D8B4613A6958030CAB085FE"><enum>(i)</enum><text display-inline="yes-display-inline">for purposes of paragraph (1), qualified property shall not fail to be treated as part of such facility solely because such qualified property is—</text> 
<subclause commented="no" display-inline="no-display-inline" id="H266D695529834BD1A8F15D03E37D8E11"><enum>(I)</enum><text display-inline="yes-display-inline">used to transport crew, goods, equipment, material, or supplies in outer space to and from such facility, or</text></subclause> <subclause commented="no" display-inline="no-display-inline" id="H785918C115BE4FFDA43AE92157883A46"><enum>(II)</enum><text>not located in outer space, and</text></subclause></clause> 
<clause commented="no" display-inline="no-display-inline" id="H2DF296CB906E4671B7DEE13B9FD58DB6"><enum>(ii)</enum><text>for purposes of paragraph (2)—</text> <subclause commented="no" display-inline="no-display-inline" id="HD1F1E0F428534A7385C3CAE9B8A4CF58"><enum>(I)</enum><text display-inline="yes-display-inline">property shall not fail to be treated as qualified property solely because such property is located in outer space,</text></subclause> 
<subclause commented="no" display-inline="no-display-inline" id="HC7CFDB81515641A09EBE85C86F1B5646"><enum>(II)</enum><text display-inline="yes-display-inline">with respect to subparagraph (A)(iv), property shall not fail to be treated as integral to the operation of such facility solely because such property is—</text> <item commented="no" display-inline="no-display-inline" id="H178D5D5EF29849B4B46D7132EC0D237B"><enum>(aa)</enum><text display-inline="yes-display-inline">used in the manner described in clause (i)(I), or</text></item> 
<item commented="no" display-inline="no-display-inline" id="H08FE90BD00C141A6A4AE745390797B5C"><enum>(bb)</enum><text>not located in outer space, and</text></item></subclause> <subclause commented="no" display-inline="no-display-inline" id="HEE5ACB9853264B6BB48AFA941AF44A72"><enum>(III)</enum><text>with respect to subparagraph (B)(ii), functions related to manufacturing shall include—</text> 
<item commented="no" display-inline="no-display-inline" id="H6382FB5EFA0144FD91C20C6DC31BFA08"><enum>(aa)</enum><text display-inline="yes-display-inline">flight control operations, </text></item> <item commented="no" display-inline="no-display-inline" id="H8BAB85125E154780AC367D8A18CEAA87"><enum>(bb)</enum><text>crew habitation in outer space,</text></item> 
<item commented="no" display-inline="no-display-inline" id="H2DA0B21CCA554FCEBD5964A290243ECA"><enum>(cc)</enum><text>repair of the facility, and</text></item> <item commented="no" display-inline="no-display-inline" id="H089F8C46912749E1812B7B409D962BF7"><enum>(dd)</enum><text> transportation of crew, goods, equipment, material, or supplies to and from the facility.</text></item></subclause></clause></subparagraph> 
<subparagraph commented="no" display-inline="no-display-inline" id="H10154B4073244C648CC5496A739B7274"><enum>(B)</enum><header>Outer space</header><text>For purposes of this paragraph, the term <term>outer space</term> shall include low-Earth orbit.</text></subparagraph> <subparagraph commented="no" display-inline="no-display-inline" id="HBBEB7CC5A8CB42F387216211F6A022C8"><enum>(C)</enum><header>Exclusion</header><text display-inline="yes-display-inline">For purposes of this subsection, the term <term>qualified property</term> shall not include a rocket or similar launch vehicle constructed for the purpose of propelling a payload from Earth into outer space.</text></subparagraph></paragraph><after-quoted-block>.</after-quoted-block></quoted-block></subsection> 
<subsection commented="no" display-inline="no-display-inline" id="HD9D559C3AF694D15AEB10D801A660F1F"><enum>(b)</enum><header>Other special rules</header><text><external-xref legal-doc="usc" parsable-cite="usc/26/50">Section 50(b)</external-xref> of the Internal Revenue Code of 1986 is amended—</text> <paragraph id="H49C74D07D138481EAAF6A3E5E6864076"><enum>(1)</enum><text>in paragraph (1)(B), by inserting <quote>or any qualified property which is part of an advanced manufacturing facility located in outer space (as such terms are defined under section 48D(b)) and held by a United States person if such property was launched from within the United States</quote> after <quote>section 168(g)(4)</quote>, and</text></paragraph> 
<paragraph commented="no" display-inline="no-display-inline" id="H40A7D46E15D847D9999D2AD5026F2E0A"><enum>(2)</enum><text>in paragraph (2)—</text> <subparagraph commented="no" display-inline="no-display-inline" id="HDE3DF2CDFB304572BFB6FD87D4B9AFED"><enum>(A)</enum><text>in subparagraph (C), by striking <quote>and</quote> at the end,</text></subparagraph> 
<subparagraph commented="no" display-inline="no-display-inline" id="H40B982803F8F4103922819936E62B282"><enum>(B)</enum><text>in subparagraph (D), by striking the period at the end and inserting <quote>; and</quote>, and</text></subparagraph> <subparagraph commented="no" display-inline="no-display-inline" id="HDD1187D0EA12431EB87C130BA6FE9BAD"><enum>(C)</enum><text>by adding at the end the following new subparagraph:</text> 
<quoted-block style="OLC" display-inline="no-display-inline" id="H475BDD55B4204A90A326498645B1EF1A"> 
<subparagraph commented="no" display-inline="no-display-inline" id="HA628F34CFDFC4AC1ACD788B77D1E22EA"><enum>(E)</enum><text>any qualified property which is part of an advanced manufacturing facility located in outer space (as such terms are defined under section 48D(b)).</text></subparagraph><after-quoted-block>.</after-quoted-block></quoted-block></subparagraph></paragraph></subsection> <subsection commented="no" display-inline="no-display-inline" id="HA90BDC2B902B47B08C8A0EAFB3D5AB76"><enum>(c)</enum><header>Effective date</header><text>The amendments made by this section shall apply to property placed in service after the date of enactment of this Act.</text></subsection> 
<subsection commented="no" display-inline="no-display-inline" id="H38CD825B385949A39788B72E1064DA52"><enum>(d)</enum><header>Rule of construction</header><text>Nothing in this Act, or the amendments made by this Act, shall be construed to create any inference with respect to the allowance or determination of the advanced manufacturing investment credit under <external-xref legal-doc="usc" parsable-cite="usc/26/48D">section 48D</external-xref> of the Internal Revenue Code of 1986 with respect to an advanced manufacturing facility located in outer space on or before the date of the enactment of this Act.</text></subsection></section> </legis-body></bill>

