<?xml version="1.0"?>
<?xml-stylesheet type="text/xsl" href="billres.xsl"?>
<!DOCTYPE bill PUBLIC "-//US Congress//DTDs/bill.dtd//EN" "bill.dtd">
<bill bill-stage="Introduced-in-House" dms-id="HA4805DBEBB784D329A97DAEDB56D5C8A" public-private="public" key="H" bill-type="olc"><metadata xmlns:dc="http://purl.org/dc/elements/1.1/">
<dublinCore>
<dc:title>119 HR 8699 IH: Safe Transit for All Act of 2026</dc:title>
<dc:publisher>U.S. House of Representatives</dc:publisher>
<dc:date>2026-05-07</dc:date>
<dc:format>text/xml</dc:format>
<dc:language>EN</dc:language>
<dc:rights>Pursuant to Title 17 Section 105 of the United States Code, this file is not subject to copyright protection and is in the public domain.</dc:rights>
</dublinCore>
</metadata>
<form>
<distribution-code display="yes">I</distribution-code><congress display="yes">119th CONGRESS</congress><session display="yes">2d Session</session><legis-num display="yes">H. R. 8699</legis-num><current-chamber>IN THE HOUSE OF REPRESENTATIVES</current-chamber><action display="yes"><action-date date="20260507">May 7, 2026</action-date><action-desc><sponsor name-id="M001241">Mr. Min</sponsor> (for himself, <cosponsor name-id="N000147">Ms. Norton</cosponsor>, and <cosponsor name-id="J000288">Mr. Johnson of Georgia</cosponsor>) introduced the following bill; which was referred to the <committee-name committee-id="HPW00">Committee on Transportation and Infrastructure</committee-name></action-desc></action><legis-type>A BILL</legis-type><official-title display="yes">To amend title 49, United States Code, to require certain recipients of Federal assistance for public transit systems to establish a program to collect data on passenger harassment on public transit systems, and for other purposes.</official-title></form><legis-body id="HE631118A8E2D4FA9BD9836B6BB88C288" style="OLC"> 
<section id="HA6BB08BAA9054DF19179CE307552E81E" section-type="section-one"><enum>1.</enum><header>Short title</header><text display-inline="no-display-inline">This Act may be cited as the <quote><short-title>Safe Transit for All Act of 2026</short-title></quote>.</text></section> <section id="HAE2DC1CEF8FD43C2BD9115DF6A724F1A" section-type="subsequent-section"><enum>2.</enum><header>Inclusion of assaults on transit passengers in public transportation safety program</header> <subsection id="HEA146BAB09F24873B84DD5D72396422A"><enum>(a)</enum><header>Public transportation agency safety plan</header><text display-inline="yes-display-inline">Section 5329(d) of title 49, United States Code, is amended—</text> 
<paragraph id="HAEACAB4F158C4C599A0D454792C5BB77"><enum>(1)</enum><text>in paragraph (1)—</text> <subparagraph id="H93CE14DABD8F4BB591327574131DCF15"><enum>(A)</enum><text>in subparagraph (I)(ii) by striking the period and inserting <quote>; and</quote>; and</text></subparagraph> 
<subparagraph id="H03CD296F974043AC99EE56F02D0EC8C4"><enum>(B)</enum><text>by adding at the end the following:</text> <quoted-block style="USC" id="H21B841EE199C4D9685C2C8208E0BB4CF" display-inline="no-display-inline"> <subparagraph id="HD80024ABA10C4F5C86875AD28D7CA327"><enum>(J)</enum><text display-inline="yes-display-inline">in the case of a recipient receiving assistance under section 5307 that is serving an urbanized area with a population of 200,000 or more, a program to collect data on street harassment on public transit systems targeted at passengers, including—</text> 
<clause id="HF28DE6B194AB45A49890E631EC6A55D7"><enum>(i)</enum><text display-inline="yes-display-inline">establishing accessible digital and in-person reporting mechanisms to collect data from passengers who have experienced or witnessed an incident of street harassment on a public transit system operated by the recipient, including the ability to collect data on— </text> <subclause id="H63B2224D4300439483AA2BA5B06E11FB"><enum>(I)</enum><text display-inline="yes-display-inline">the frequency, type, location, and time of the incident experienced or witnessed by the passenger, including whether such street harassment was verbal harassment, a physical assault, or a sexual assault;</text></subclause> 
<subclause id="HD9C01F23CDC74DD98EC696797A81F989"><enum>(II)</enum><text display-inline="yes-display-inline">the demographic information of the passenger or passengers that experienced the incident, including race, ethnicity, religion, age, disability, income, primary language, sex, and sexual orientation;</text></subclause> <subclause id="HD61161FDD98742DBAC5730734175BD6F"><enum>(III)</enum><text display-inline="yes-display-inline">the actual or perceived characteristics that may have served as the basis for the incident; and</text></subclause> 
<subclause id="H3863BB4965BC44AD8367256B87FFD10D"><enum>(IV)</enum><text display-inline="yes-display-inline">the impact of the incident on the passenger, including whether and in what way street harassment affects the use of public transit by the passenger; </text></subclause> </clause> <clause id="HEEE624ECC881485C95168394B87BA784"><enum>(ii)</enum><text display-inline="yes-display-inline">collecting data and conducting outreach in multiple languages to understand safety concerns and experiences of passengers with limited English language proficiency;</text></clause> 
<clause id="H35F8DFDE3BAE4DE4ACDBE511623221E7"><enum>(iii)</enum><text display-inline="yes-display-inline">in a timely manner after data is collected pursuant to clauses (i) and (ii), publishing on a publicly available website the data collected, excluding any personally identifiable information; and</text></clause> <clause id="HFB44040EDBE3461D977F89D01A026DCB"><enum>(iv)</enum><text display-inline="yes-display-inline">establishing protocols for responding to reports of street harassment received through the reporting mechanisms established in clause (i).</text></clause> </subparagraph><after-quoted-block>; and</after-quoted-block></quoted-block></subparagraph></paragraph> 
<paragraph id="HDD6C293ED0C8449D9D79DF338CA4E751"><enum>(2)</enum><text>by adding at the end the following:</text> <quoted-block style="USC" id="H0AC1D97586BF49F98BD8CA977553F2AB" display-inline="no-display-inline"> <paragraph id="HF6B8E1A0852149F99E80C016F7EEC931"><enum>(6)</enum><header>Definition of street harassment</header><text display-inline="yes-display-inline">In this subsection, the term <term>street harassment</term> means any word, gesture, or other action directed at an individual because of an actual or perceived personal characteristic of the individual, including a characteristic protected under title VI or VII of the Civil Rights Act of 1964 (<external-xref legal-doc="usc" parsable-cite="usc/42/2000d">42 U.S.C. 2000d et seq.</external-xref>) or the Age Discrimination in Employment Act of 1967 (<external-xref legal-doc="usc" parsable-cite="usc/29/621">29 U.S.C. 621 et seq.</external-xref>), in a public place, without the consent of the individual, in which the individual experiences such word, gesture, or action as intimidating or threatening to the safety of the individual.</text></paragraph><after-quoted-block>.</after-quoted-block></quoted-block></paragraph></subsection> 
<subsection id="H960ADF17F619420881712818C8649FA8"><enum>(b)</enum><header>National transit database</header><text>Section 5335 of title 49, United States Code, is amended—</text> <paragraph id="H94A1BD0E7B3F41AF93D593F211A39A40"><enum>(1)</enum><text display-inline="yes-display-inline">in subsection (c)—</text> 
<subparagraph id="HEB4D56268DF944B6BC702F63138C1703"><enum>(A)</enum><text>in paragraph (2) by striking <quote>and</quote>;</text></subparagraph> <subparagraph id="H36B5774EF74543C69A48CCE3C9553ECA"><enum>(B)</enum><text>in paragraph (3) by striking the period and inserting <quote>; and</quote>; and</text></subparagraph> 
<subparagraph id="H6E3AB7029B1D4BB385CAF529B576EAC7"><enum>(C)</enum><text>by adding at the end the following:</text> <quoted-block style="USC" id="H053EE34504174136B55066DA264356E5" display-inline="no-display-inline"> <paragraph id="H4595F5F1B6E043F38B8C676DAA744B7E"><enum>(4)</enum><text display-inline="yes-display-inline">any data on street harassment of passengers collected by the recipient pursuant to section 5329(d).</text></paragraph><after-quoted-block>.</after-quoted-block></quoted-block></subparagraph></paragraph> </subsection></section> 
</legis-body></bill>

