{
  "action": {
    "description": "Passed Senate without amendment by Unanimous Consent. (consideration: CR S2709-2710; text: CR S2709-2710)",
    "occurred_at": "2025-04-30T04:00:00+00:00",
    "jurisdiction_id": "~{\"classification\": \"upper\"}",
    "session_id": "119",
    "entity_type": "bill",
    "classifications": [],
    "related_entities": [],
    "sources": [
      {
        "url": "https://www.govinfo.gov/bulkdata/BILLSTATUS/119/s/BILLSTATUS-119s616.xml",
        "note": ""
      },
      {
        "url": "https://congress.gov/bill/119th-congress/senate-bill/616",
        "note": ""
      }
    ]
  },
  "bill_id": "S 616"
}